metrica_loader/__init__.py
metrica_loader/am/__init__.py
metrica_loader/am/am.py
metrica_loader/auth/__init__.py
metrica_loader/auth/auth.py
metrica_loader/ym/__init__.py
metrica_loader/ym/ym.py
metrica_loader-1.3.dist-info/METADATA
metrica_loader-1.3.dist-info/WHEEL
metrica_loader-1.3.dist-info/top_level.txt
metrica_loader-1.3.dist-info/RECORD
