Metadata-Version: 2.1
Name: metrica-loader
Version: 1.3
Summary: UNKNOWN
Home-page: UNKNOWN
License: UNKNOWN
Platform: UNKNOWN
